{"cameraMode":{"drawMode":0,"name":"Shaded","section":"Shading Mode"},"sceneLighting":true,"audioPlay":false,"sceneViewState":{"m_AlwaysRefresh":false,"showFog":true,"showSkybox":true,"showFlares":true,"showImageEffects":true,"showParticleSystems":true,"showVisualEffectGraphs":true,"m_FxEnabled":true},"in2DMode":false,"pivot":{"x":294.08935546875,"y":792.6110229492188,"z":28.842479705810548},"rotation":{"x":-0.14082755148410798,"y":0.8049265742301941,"z":-0.21138034760951997,"w":-0.5362651944160461},"size":7.071067810058594,"orthographic":false}